audiotimer/__init__.py
audiotimer/__main__.py
audiotimer/config.ini
audiotimer/flags.py
audiotimer/helpers.py
audiotimer/slack_ping.py
audiotimer-0.4.0.dist-info/METADATA
audiotimer-0.4.0.dist-info/WHEEL
audiotimer-0.4.0.dist-info/entry_points.txt
audiotimer-0.4.0.dist-info/top_level.txt
audiotimer-0.4.0.dist-info/RECORD
